setup.py
unidbm/__init__.py
unidbm/utils.py
unidbm.egg-info/PKG-INFO
unidbm.egg-info/SOURCES.txt
unidbm.egg-info/dependency_links.txt
unidbm.egg-info/top_level.txt
unidbm/backends/__init__.py
unidbm/backends/kyotocabinet.py
unidbm/backends/semidbm.py
unidbm/backends/sqlite.py
unidbm/middlewares/__init__.py
unidbm/middlewares/compress.py
unidbm/middlewares/json.py
unidbm/middlewares/pickle.py
unidbm/middlewares/string.py